BaseCls/__init__.py
BaseDet/__init__.py
megengine/__init__.py
BaseDet-0.0.1rc1.dist-info/METADATA
BaseDet-0.0.1rc1.dist-info/WHEEL
BaseDet-0.0.1rc1.dist-info/top_level.txt
BaseDet-0.0.1rc1.dist-info/RECORD
